[{"name":"안녕하세요.","stageID":1,"questionIDList":[1,2,3,4,5,6]},{"name":"나는 사과를 먹어요.","stageID":2,"questionIDList":[11,12,13,14,15,16,17,18,19,20]},{"name":"그는 커피를 마셔요.","stageID":3,"questionIDList":[21,22,23,24,25,26,27,28,29,30]},{"name":"우리는 학교에 가요.","stageID":4,"questionIDList":[31,32,33,34,35,36,37,38,39,40]},{"name":"나는 남자에요.","stageID":5,"questionIDList":[41,42,43,44,45,46,47,48,49,50]},{"name":"아이는 엄마를 사랑해요.","stageID":6,"questionIDList":[51,52,53,54,55,56,57,58,59,60]},{"name":"아기는 장남감을 좋아해요.","stageID":7,"questionIDList":[61,62,63,64,65,66,67,68,69,70]},{"name":"나는 샤워를 싫어해요.","stageID":8,"questionIDList":[71,72,73,74,75,76,77,78,79,80]},{"name":"나는 버스를 타요.","stageID":9,"questionIDList":[81,82,83,84,85,86,87,88,89,90]},{"name":"나는 책을 읽어요.","stageID":10,"questionIDList":[91,92,93,94,95,96,97,98,99,100]},{"name":"나는 고기를 안먹어요.","stageID":11,"questionIDList":[101,102,103,104,105,106,107,108,109,110]},{"name":"나는 주스를 안마셔요.","stageID":12,"questionIDList":[111,112,113,114,115,116,117,118,119,120]},{"name":"나는 극장에 안가요.","stageID":13,"questionIDList":[121,122,123,124,125,126,127,128,129,130]},{"name":"저는 학생이 아니에요.","stageID":14,"questionIDList":[131,132,133,134,135,136,137,138,139,140]},{"name":"저는 농구를 안좋아해요.","stageID":15,"questionIDList":[141,142,143,144,145,146,147,148,149,150]},{"name":"우리는 지갑 안사요.","stageID":16,"questionIDList":[151,152,153,154,155,156,157,158,159,160]},{"name":"우리는 선풍기 안팔아요.","stageID":17,"questionIDList":[161,162,163,164,165,166,167,168,169,170]},{"name":"그는 김치 안만들어요.","stageID":18,"questionIDList":[171,172,173,174,175,176,177,178,179,180]},{"name":"그녀는 영화 안봐요.","stageID":19,"questionIDList":[181,182,183,184,185,186,187,188,189,190]},{"name":"아니요.","stageID":20,"questionIDList":[191,192,193,194,195,196,197,198,199,200]},{"name":"너 지금 점심 먹니?","stageID":21,"questionIDList":[201,202,203,204,205,206,207,208,209,210]},{"name":"너 학교 가니?","stageID":22,"questionIDList":[211,212,213,214,215,216,217,218,219,220]},{"name":"그가 나를 사랑할까?","stageID":23,"questionIDList":[221,222,223,224,225,226,227,228,229,230]},{"name":"그녀가 한국을 좋아할까?","stageID":24,"questionIDList":[231,232,233,234,235,236,237,238,239,240]},{"name":"춥니?","stageID":25,"questionIDList":[241,242,243,244,245,246,247,248,249,250]},{"name":"배고프니?","stageID":26,"questionIDList":[251,252,253,254,255,256,257,258,259,260]},{"name":"졸리니?","stageID":27,"questionIDList":[261,262,263,264,265,266,267,268,269,270]},{"name":"멋있니?","stageID":28,"questionIDList":[271,272,273,274,275,276,277,278,279,280]},{"name":"숙제 하니?","stageID":29,"questionIDList":[281,282,283,284,285,286,287,288,289,290]},{"name":"언제, 어디서, 무엇을, 어떻게, 왜, 누가.","stageID":30,"questionIDList":[291,292,293,294,295,296,297,298,299,300]},{"name":"Stage 31","stageID":31,"questionIDList":[301,302,303,304,305,306,307,308,309,310]},{"name":"Stage 32","stageID":32,"questionIDList":[311,312,313,314,315,316,317,318,319,320]},{"name":"Stage 33","stageID":33,"questionIDList":[321,322,323,324,325,326,327,328,329,330]},{"name":"Stage 34","stageID":34,"questionIDList":[331,332,333,334,335,336,337,338,339,340]},{"name":"Stage 35","stageID":35,"questionIDList":[341,342,343,344,345,346,347,348,349,350]},{"name":"Stage 36","stageID":36,"questionIDList":[351,352,353,354,355,356,357,358,359,360]},{"name":"Stage 37","stageID":37,"questionIDList":[361,362,363,364,365,366,367,368,369,370]},{"name":"Stage 38","stageID":38,"questionIDList":[371,372,373,374,375,376,377,378,379,380]},{"name":"Stage 39","stageID":39,"questionIDList":[381,382,383,384,385,386,387,388,389,390]},{"name":"Stage 40","stageID":40,"questionIDList":[391,392,393,394,395,396,397,398,399,400]},{"name":"Stage 41","stageID":41,"questionIDList":[401,402,403,404,405,406,407,408,409,410]},{"name":"Stage 42","stageID":42,"questionIDList":[411,412,413,414,415,416,417,418,419,420]},{"name":"Stage 43","stageID":43,"questionIDList":[421,422,423,424,425,426,427,428,429,430]},{"name":"Stage 44","stageID":44,"questionIDList":[431,432,433,434,435,436,437,438,439,440]},{"name":"Stage 45","stageID":45,"questionIDList":[441,442,443,444,445,446,447,448,449,450]},{"name":"Stage 46","stageID":46,"questionIDList":[451,452,453,454,455,456,457,458,459,460]},{"name":"Stage 47","stageID":47,"questionIDList":[461,462,463,464,465,466,467,468,469,470]},{"name":"Stage 48","stageID":48,"questionIDList":[471,472,473,474,475,476,477,478,479,480]},{"name":"Stage 49","stageID":49,"questionIDList":[481,482,483,484,485,486,487,488,489,490]},{"name":"Stage 50","stageID":50,"questionIDList":[491,492,493,494,495,496,497,498,499,500]},{"name":"Stage 51","stageID":51,"questionIDList":[501,502,503,504,505,506,507,508,509,510]},{"name":"Stage 52","stageID":52,"questionIDList":[511,512,513,514,515,516,517,518,519,520]},{"name":"Stage 53","stageID":53,"questionIDList":[521,522,523,524,525,526,527,528,529,530]},{"name":"Stage 54","stageID":54,"questionIDList":[531,532,533,534,535,536,537,538,539,540]},{"name":"Stage 55","stageID":55,"questionIDList":[541,542,543,544,545,546,547,548,549,550]},{"name":"Stage 56","stageID":56,"questionIDList":[551,552,553,554,555,556,557,558,559,560]},{"name":"Stage 57","stageID":57,"questionIDList":[561,562,563,564,565,566,567,568,569,570]},{"name":"Stage 58","stageID":58,"questionIDList":[571,572,573,574,575,576,577,578,579,580]},{"name":"Stage 59","stageID":59,"questionIDList":[581,582,583,584,585,586,587,588,589,590]},{"name":"Stage 60","stageID":60,"questionIDList":[591,592,593,594,595,596,597,598,599,600]},{"name":"Stage 61","stageID":61,"questionIDList":[601,602,603,604,605,606,607,608,609,610]},{"name":"Stage 62","stageID":62,"questionIDList":[611,612,613,614,615,616,617,618,619,620]},{"name":"Stage 63","stageID":63,"questionIDList":[621,622,623,624,625,626,627,628,629,630]},{"name":"Stage 64","stageID":64,"questionIDList":[631,632,633,634,635,636,637,638,639,640]},{"name":"Stage 65","stageID":65,"questionIDList":[641,642,643,644,645,646,647,648,649,650]},{"name":"Stage 66","stageID":66,"questionIDList":[651,652,653,654,655,656,657,658,659,660]},{"name":"Stage 67","stageID":67,"questionIDList":[661,662,663,664,665,666,667,668,669,670]},{"name":"Stage 68","stageID":68,"questionIDList":[671,672,673,674,675,676,677,678,679,680]},{"name":"Stage 69","stageID":69,"questionIDList":[681,682,683,684,685,686,687,688,689,690]},{"name":"Stage 70","stageID":70,"questionIDList":[691,692,693,694,695,696,697,698,699,700]},{"name":"Stage 71","stageID":71,"questionIDList":[701,702,703,704,705,706,707,708,709,710]},{"name":"Stage 72","stageID":72,"questionIDList":[711,712,713,714,715,716,717,718,719,720]},{"name":"Stage 73","stageID":73,"questionIDList":[721,722,723,724,725,726,727,728,729,730]},{"name":"Stage 74","stageID":74,"questionIDList":[731,732,733,734,735,736,737,738,739,740]},{"name":"Stage 75","stageID":75,"questionIDList":[741,742,743,744,745,746,747,748,749,750]},{"name":"Stage 76","stageID":76,"questionIDList":[751,752,753,754,755,756,757,758,759,760]},{"name":"Stage 77","stageID":77,"questionIDList":[761,762,763,764,765,766,767,768,769,770]},{"name":"Stage 78","stageID":78,"questionIDList":[771,772,773,774,775,776,777,778,779,780]},{"name":"Stage 79","stageID":79,"questionIDList":[781,782,783,784,785,786,787,788,789,790]},{"name":"Stage 80","stageID":80,"questionIDList":[791,792,793,794,795,796,797,798,799,800]},{"name":"Stage 81","stageID":81,"questionIDList":[801,802,803,804,805,806,807,808,809,810]},{"name":"Stage 82","stageID":82,"questionIDList":[811,812,813,814,815,816,817,818,819,820]},{"name":"Stage 83","stageID":83,"questionIDList":[821,822,823,824,825,826,827,828,829,830]},{"name":"Stage 84","stageID":84,"questionIDList":[831,832,833,834,835,836,837,838,839,840]},{"name":"Stage 85","stageID":85,"questionIDList":[841,842,843,844,845,846,847,848,849,850]},{"name":"Stage 86","stageID":86,"questionIDList":[851,852,853,854,855,856,857,858,859,860]},{"name":"Stage 87","stageID":87,"questionIDList":[861,862,863,864,865,866,867,868,869,870]},{"name":"Stage 88","stageID":88,"questionIDList":[871,872,873,874,875,876,877,878,879,880]},{"name":"Stage 89","stageID":89,"questionIDList":[881,882,883,884,885,886,887,888,889,890]},{"name":"Stage 90","stageID":90,"questionIDList":[891,892,893,894,895,896,897,898,899,900]},{"name":"Stage 91","stageID":91,"questionIDList":[901,902,903,904,905,906,907,908,909,910]},{"name":"Stage 92","stageID":92,"questionIDList":[911,912,913,914,915,916,917,918,919,920]},{"name":"Stage 93","stageID":93,"questionIDList":[921,922,923,924,925,926,927,928,929,930]},{"name":"Stage 94","stageID":94,"questionIDList":[931,932,933,934,935,936,937,938,939,940]},{"name":"Stage 95","stageID":95,"questionIDList":[941,942,943,944,945,946,947,948,949,950]},{"name":"Stage 96","stageID":96,"questionIDList":[951,952,953,954,955,956,957,958,959,960]},{"name":"Stage 97","stageID":97,"questionIDList":[961,962,963,964,965,966,967,968,969,970]},{"name":"Stage 98","stageID":98,"questionIDList":[971,972,973,974,975,976,977,978,979,980]},{"name":"Stage 99","stageID":99,"questionIDList":[981,982,983,984,985,986,987,988,989,990]},{"name":"Stage 100","stageID":100,"questionIDList":[991,992,993,994,995,996,997,998,999,1000]}]